trip_pay_payment/__init__.py
trip_pay_payment/api_client.py
trip_pay_payment/api_response.py
trip_pay_payment/configuration.py
trip_pay_payment/exceptions.py
trip_pay_payment/py.typed
trip_pay_payment/rest.py
trip_pay_payment/api/__init__.py
trip_pay_payment/api/account_api.py
trip_pay_payment/api/account_mappings_api.py
trip_pay_payment/api/activity_stream_api.py
trip_pay_payment/api/affiliate_api.py
trip_pay_payment/api/agent_api.py
trip_pay_payment/api/application_api.py
trip_pay_payment/api/contract_api.py
trip_pay_payment/api/external_event_api.py
trip_pay_payment/api/managing_entity_api.py
trip_pay_payment/api/mapping_api.py
trip_pay_payment/api/notification_api.py
trip_pay_payment/api/notification_lightweight_api.py
trip_pay_payment/api/payout_api.py
trip_pay_payment/api/ping_api.py
trip_pay_payment/api/send_notification_controller_api.py
trip_pay_payment/api/webhook_api.py
trip_pay_payment/models/__init__.py
trip_pay_payment/models/account.py
trip_pay_payment/models/account_status_entry.py
trip_pay_payment/models/account_status_response.py
trip_pay_payment/models/acquirer.py
trip_pay_payment/models/acquirer_credentials.py
trip_pay_payment/models/activity_stream.py
trip_pay_payment/models/activity_stream_user.py
trip_pay_payment/models/address.py
trip_pay_payment/models/affiliate_details_request.py
trip_pay_payment/models/affiliate_information.py
trip_pay_payment/models/aggregate_booking_contract_cancellation_state.py
trip_pay_payment/models/aggregate_booking_contract_capture_currencies_by_account_response.py
trip_pay_payment/models/aggregate_descriptor.py
trip_pay_payment/models/application.py
trip_pay_payment/models/authenticated_user.py
trip_pay_payment/models/available_funds.py
trip_pay_payment/models/bank_account.py
trip_pay_payment/models/beneficiary.py
trip_pay_payment/models/beneficiary_aggregate_data.py
trip_pay_payment/models/beneficiary_charge.py
trip_pay_payment/models/booking_contract.py
trip_pay_payment-0.0.45.dist-info/licenses/LICENSE
trip_pay_payment-0.0.45.dist-info/METADATA
trip_pay_payment-0.0.45.dist-info/WHEEL
trip_pay_payment-0.0.45.dist-info/top_level.txt
trip_pay_payment-0.0.45.dist-info/RECORD
