Metadata-Version: 2.4
Name: trip_pay_payment
Version: 0.0.45
Summary: Wink Payment API
Home-page: https://github.com/wink-travel/trip-pay-sdk-python.git
Author: Bjorn Harvold
Author-email: Bjorn Harvold <bjorn@wink.travel>
License:                                  Apache License
Keywords: OpenAPI,OpenAPI-Generator,Wink Payment API
License-File: LICENSE
Dynamic: author
Dynamic: home-page
Dynamic: license-file
